{
  "benchmark_config": {
    "budget_s": 3.0,
    "max_depth": 2,
    "tasks": "examples/tasks"
  },
  "date": "2026-06-17T15:02:41.857456+00:00",
  "device": "cpu",
  "dtype": "n/a",
  "git_commit": null,
  "hardware": {
    "cuda_available": false,
    "cuda_device": null,
    "platform": "Linux-4.4.0-x86_64-with-glibc2.41",
    "python": "3.13.5",
    "torch": "2.10.0+cpu"
  },
  "limitations": [
    "Small DSL and demo tasks.",
    "Avoid public-eval leakage."
  ],
  "model_config": {},
  "name": "symbolic_arc",
  "raw_metrics": {
    "pass_at_1": 1.0,
    "tasks": [
      {
        "candidates_tested": 3,
        "elapsed_s": 0.00015715600000021368,
        "failure": null,
        "predictions": [
          [
            [
              8,
              0,
              7
            ]
          ]
        ],
        "program": "rotate180",
        "solved": true,
        "task_id": "mirror_y_demo"
      },
      {
        "candidates_tested": 2,
        "elapsed_s": 0.00012694899999132758,
        "failure": null,
        "predictions": [
          [
            [
              9,
              7
            ],
            [
              1,
              8
            ]
          ]
        ],
        "program": "rotate90",
        "solved": true,
        "task_id": "rotate90_demo"
      }
    ]
  },
  "recommendation": "TINY-TRAIN ONLY \u2014 promising but unproven.",
  "result_type": "zero-training symbolic solver result",
  "seed": 0,
  "summary": "Explicit symbolic program search. Not neural reasoning."
}